CHANGELOG.rst
sshh/__init__.py
sshh/logging.py
sshh/proc.py
sshh/regstry.py
sshh/runner.py
sshh/sshh.py
sshh/sshh_add.py
sshh/sshh_agent.py
sshh/sshh_askpass.py
sshh/sshh_config.py
sshh-0.10.0.dist-info/entry_points.txt
sshh-0.10.0.dist-info/LICENSE
sshh-0.10.0.dist-info/WHEEL
sshh-0.10.0.dist-info/METADATA
sshh-0.10.0.dist-info/RECORD
