Metadata-Version: 2.1
Name: sshh
Version: 0.10.0
Summary: sshh is an ssh helper tool for batch registration of ssh private keys in ssh-agent
Home-page: https://github.com/shimizukawa/sshh
License: Apache-2.0
Keywords: ssh,utility
Author: Takayuki Shimizukawa
Author-email: shimizukawa@gmail.com
Requires-Python: >=3.6
Classifier: Development Status :: 4 - Beta
Classifier: Environment :: Console
Classifier: Environment :: MacOS X
Classifier: Intended Audience :: Developers
Classifier: License :: OSI Approved :: Apache Software License
Classifier: Operating System :: MacOS :: MacOS X
Classifier: Operating System :: POSIX :: BSD
Classifier: Operating System :: POSIX :: Linux
Classifier: Operating System :: Unix
Classifier: Programming Language :: Python :: 3
Classifier: Programming Language :: Python :: 3.6
Classifier: Programming Language :: Python :: 3.7
Classifier: Topic :: Utilities
Requires-Dist: cryptography (>=2.6)
Project-URL: Documentation, https://github.com/shimizukawa/sshh/blob/master/README.rst
Project-URL: Repository, https://github.com/shimizukawa/sshh
